{
    "__typename": "GraphImage",
    "comments_disabled": false,
    "dimensions": {
        "height": 810,
        "width": 1080
    },
    "display_url": "https://instagram.fdel3-2.fna.fbcdn.net/v/t51.2885-15/e35/s1080x1080/79271808_846102965821987_1566999215932991981_n.jpg?_nc_ht=instagram.fdel3-2.fna.fbcdn.net&_nc_cat=107&_nc_ohc=CyX6RCYuTzUAX8VVYux&oh=f089939024e0343463ee3dd4b95971ae&oe=5EA59311",
    "edge_liked_by": {
        "count": 56
    },
    "edge_media_to_caption": {
        "edges": [
            {
                "node": {
                    "text": "#mercedesbenz \ud83d\udc8e"
                }
            }
        ]
    },
    "edge_media_to_comment": {
        "count": 1
    },
    "id": "2205226963172610068",
    "is_video": false,
    "owner": {
        "id": "418056003"
    },
    "shortcode": "B6aij09BFAU",
    "taken_at_timestamp": 1577103561,
    "thumbnail_src": "https://instagram.fdel3-2.fna.fbcdn.net/v/t51.2885-15/sh0.08/e35/c180.0.1080.1080a/s640x640/79271808_846102965821987_1566999215932991981_n.jpg?_nc_ht=instagram.fdel3-2.fna.fbcdn.net&_nc_cat=107&_nc_ohc=CyX6RCYuTzUAX8VVYux&oh=83153eb5e5e1e97e2943fd68e9488303&oe=5EA652D2"
}