{
    "__typename": "GraphImage",
    "comments_disabled": false,
    "dimensions": {
        "height": 1350,
        "width": 1080
    },
    "display_url": "https://instagram.fdel3-2.fna.fbcdn.net/v/t51.2885-15/e35/79750612_682118895652774_7649928297203294273_n.jpg?_nc_ht=instagram.fdel3-2.fna.fbcdn.net&_nc_cat=110&_nc_ohc=LO4gAEvciXkAX-qWcHq&oh=b422114887a5c0189dc3450535f22936&oe=5EA448D8",
    "edge_liked_by": {
        "count": 232
    },
    "edge_media_to_caption": {
        "edges": [
            {
                "node": {
                    "text": "We Have Nothing to Lose and a World to See !.\nNICE START 2020.\n@theraviz\n#newyearseve  #newyear  #leela #raviz #kovalam #chilling #friends #endlesssea #santa #luxury #fivestar #trivandrum #luxurylifestyle #iphone #galaxy"
                }
            }
        ]
    },
    "edge_media_to_comment": {
        "count": 29
    },
    "id": "2212702947414764138",
    "is_video": false,
    "owner": {
        "id": "1990178277"
    },
    "shortcode": "B61GZt2Hepq",
    "taken_at_timestamp": 1577994768,
    "thumbnail_src": "https://instagram.fdel3-2.fna.fbcdn.net/v/t51.2885-15/sh0.08/e35/c0.135.1080.1080a/s640x640/79750612_682118895652774_7649928297203294273_n.jpg?_nc_ht=instagram.fdel3-2.fna.fbcdn.net&_nc_cat=110&_nc_ohc=LO4gAEvciXkAX-qWcHq&oh=e8fd1a8afc12d71e5637156feab0e603&oe=5EA56E5C"
}