{
    "__typename": "GraphImage",
    "comments_disabled": false,
    "dimensions": {
        "height": 1080,
        "width": 1080
    },
    "display_url": "https://instagram.fdel3-1.fna.fbcdn.net/v/t51.2885-15/e35/81730698_477226389646149_6742846124239762185_n.jpg?_nc_ht=instagram.fdel3-1.fna.fbcdn.net&_nc_cat=109&_nc_ohc=uw_ljZ_JAzAAX8nL43n&oh=c44e9a0cfee079d0748b49b3891a8100&oe=5EA6557D",
    "edge_liked_by": {
        "count": 1
    },
    "edge_media_to_caption": {
        "edges": [
            {
                "node": {
                    "text": "Dish - daal\n\n#raviz #ravizguildford #photooftheday #dinner #dinnerideas #dinnerparty #travelguide #traveller #guildford #drinkoftheday #soup #foodphotography #indianfood #asianfood #daal #lentils"
                }
            }
        ]
    },
    "edge_media_to_comment": {
        "count": 0
    },
    "id": "2214196427088099265",
    "is_video": false,
    "owner": {
        "id": "310924143"
    },
    "shortcode": "B66Z-tLhnfB",
    "taken_at_timestamp": 1578172804,
    "thumbnail_src": "https://instagram.fdel3-1.fna.fbcdn.net/v/t51.2885-15/sh0.08/e35/s640x640/81730698_477226389646149_6742846124239762185_n.jpg?_nc_ht=instagram.fdel3-1.fna.fbcdn.net&_nc_cat=109&_nc_ohc=uw_ljZ_JAzAAX8nL43n&oh=108fec8acb553fe076cd0e578ae4d00a&oe=5EA48D9A"
}