{
    "__typename": "GraphImage",
    "comments_disabled": false,
    "dimensions": {
        "height": 1080,
        "width": 1080
    },
    "display_url": "https://instagram.fdel3-1.fna.fbcdn.net/v/t51.2885-15/e35/82756253_2469952563271500_6404040489861608548_n.jpg?_nc_ht=instagram.fdel3-1.fna.fbcdn.net&_nc_cat=100&_nc_ohc=1lytmsHtgdIAX85cIl_&oh=fd39f760dbbe4ab1a3921b84394381fb&oe=5EA59554",
    "edge_liked_by": {
        "count": 46
    },
    "edge_media_to_caption": {
        "edges": [
            {
                "node": {
                    "text": "Travel is all about a new way of seeing things and doing our part to put tourism on a sustainable path. All of the world\u2019s treasures will be more enjoyable and lasting places to experience for future generations when we embrace the ideals of sustainable tourism.\n\n#NationalTourismDay #IncredibleIndia #NationalTourismDay2020 #TourismDay #KeralaTourism  #Raviz #TheRaviz #RavizKovalam #TheRavizKovalam\n#Kovalam #Kerala #Tourism #KeralaTourism #LuxuryResorts #Resorts #Destinations #TripAdvisor #CondeNastTraveller #TravelandLeisure #LonelyPlanet #WeekendGetaway"
                }
            }
        ]
    },
    "edge_media_to_comment": {
        "count": 0
    },
    "id": "2228829753700553004",
    "is_video": false,
    "owner": {
        "id": "13829535608"
    },
    "shortcode": "B7uZNomJJEs",
    "taken_at_timestamp": 1579917233,
    "thumbnail_src": "https://instagram.fdel3-1.fna.fbcdn.net/v/t51.2885-15/sh0.08/e35/s640x640/82756253_2469952563271500_6404040489861608548_n.jpg?_nc_ht=instagram.fdel3-1.fna.fbcdn.net&_nc_cat=100&_nc_ohc=1lytmsHtgdIAX85cIl_&oh=9565757bf67e21199d8ce6ee97114cda&oe=5EA59B6A"
}