{
    "__typename": "GraphImage",
    "comments_disabled": false,
    "dimensions": {
        "height": 1080,
        "width": 1080
    },
    "display_url": "https://instagram.fdel3-1.fna.fbcdn.net/v/t51.2885-15/e35/89266457_2460326844277884_7092734583604932785_n.jpg?_nc_ht=instagram.fdel3-1.fna.fbcdn.net&_nc_cat=100&_nc_ohc=7Ts9nkXE8cUAX_IMuZ_&oh=389d5f672a2b3956a7c94f493742538f&oe=5EA3571B",
    "edge_liked_by": {
        "count": 55
    },
    "edge_media_to_caption": {
        "edges": [
            {
                "node": {
                    "text": "This Holi, wishing you nature\u2019s beautiful bounty, splashes of color, joy and spirited goodness.\n\n#HappyHoli #HoliFestival #FestivalColours #KeralaTourism #Kerala #LuxuryResort #Raviz #TheRaviz #TravelDestinations #Luxury #GodsOwnCountry #DestinationKerala #Destinations #ResortsinKerala #Travel #Wanderlust #RavizKadavu #RavizCalicut #RavizAshtamudi #RavizKovalam #HappyHoli2020 #RangWaliHoli #FestivalOfColors #HoliParty #HoliFest #Holi #ColorFest #HoliHai"
                }
            }
        ]
    },
    "edge_media_to_comment": {
        "count": 0
    },
    "id": "2261543638303342537",
    "is_video": false,
    "owner": {
        "id": "2137015239"
    },
    "shortcode": "B9infT1HX_J",
    "taken_at_timestamp": 1583817032,
    "thumbnail_src": "https://instagram.fdel3-1.fna.fbcdn.net/v/t51.2885-15/sh0.08/e35/s640x640/89266457_2460326844277884_7092734583604932785_n.jpg?_nc_ht=instagram.fdel3-1.fna.fbcdn.net&_nc_cat=100&_nc_ohc=7Ts9nkXE8cUAX_IMuZ_&oh=d9685516886b606fb88b5b4984debfa0&oe=5EA44DA1"
}