{
    "__typename": "GraphImage",
    "comments_disabled": false,
    "dimensions": {
        "height": 1080,
        "width": 1080
    },
    "display_url": "https://instagram.fdel3-2.fna.fbcdn.net/v/t51.2885-15/e35/s1080x1080/90350336_511024302915334_1299957679215521894_n.jpg?_nc_ht=instagram.fdel3-2.fna.fbcdn.net&_nc_cat=110&_nc_ohc=UJOTzEC9kfYAX95xDg6&oh=908f764d61fcb5cced999d2889ef8b8c&oe=5EA3E93D",
    "edge_liked_by": {
        "count": 148
    },
    "edge_media_to_caption": {
        "edges": [
            {
                "node": {
                    "text": "\u2600\ufe0f \u2800\u2800\u2800\u2800\u2800\u2800\u2800\u2800\u2800\n\u2800\u2800\u2800\u2800\u2800\u2800\u2800\u2800\u2800\n\u2800\u2800\u2800\u2800\u2800\u2800\u2800\u2800\u2800\n\u2800\u2800\u2800\u2800\u2800\u2800\u2800\u2800\u2800\n\u2800\u2800\u2800\u2800\u2800\u2800\u2800\u2800\u2800\n\u2800\u2800\u2800\u2800\u2800\u2800\u2800\u2800\u2800\n\u2800\u2800\u2800\u2800\u2800\u2800\u2800\u2800\u2800\n\u2800\u2800\u2800\u2800\u2800\u2800\u2800\u2800\u2800\n\u2800\u2800\u2800\u2800\u2800\u2800\u2800\u2800\u2800 #scheveningen #scheveningenbeach #depier #denhaag #thehague #thehaguedaily #canon #cokin #longexposure #longexposure_shots #photography #artofvisuals #lensbible #landscape #beach #sea #beachlife #summer #urban #urbanphotography #urbanlandscape"
                }
            }
        ]
    },
    "edge_media_to_comment": {
        "count": 8
    },
    "id": "2270478485335503155",
    "is_video": false,
    "owner": {
        "id": "4022026196"
    },
    "shortcode": "B-CXCcklvEz",
    "taken_at_timestamp": 1584882148,
    "thumbnail_src": "https://instagram.fdel3-2.fna.fbcdn.net/v/t51.2885-15/sh0.08/e35/s640x640/90350336_511024302915334_1299957679215521894_n.jpg?_nc_ht=instagram.fdel3-2.fna.fbcdn.net&_nc_cat=110&_nc_ohc=UJOTzEC9kfYAX95xDg6&oh=ef1632ff28c8b74b4110fd0565e4293a&oe=5EA5DF0C"
}