{
    "__typename": "GraphImage",
    "comments_disabled": false,
    "dimensions": {
        "height": 1080,
        "width": 1080
    },
    "display_url": "https://instagram.fdel3-2.fna.fbcdn.net/v/t51.2885-15/e35/90674194_523507438567135_9049331123891284988_n.jpg?_nc_ht=instagram.fdel3-2.fna.fbcdn.net&_nc_cat=107&_nc_ohc=MB1vL-b8YyIAX-v37_I&oh=c09c24017748f467c6fa2f953556daf7&oe=5EA491C4",
    "edge_liked_by": {
        "count": 0
    },
    "edge_media_to_caption": {
        "edges": [
            {
                "node": {
                    "text": "Raquete de Beach Tennis Vision Super Carbon\nR$1.119,90\n\nhttps://itenis.com.br/raquete-de-beach-tennis-vision-super-carbon-hexagon-50-2019-10511.html\n\n#itenis #beachtennis #raquete #raquetedebeachtennis #raquetedebeac #praia #beach"
                }
            }
        ]
    },
    "edge_media_to_comment": {
        "count": 0
    },
    "id": "2272815655399152133",
    "is_video": false,
    "owner": {
        "id": "4325095127"
    },
    "shortcode": "B-Kqcv0A1oF",
    "taken_at_timestamp": 1585160761,
    "thumbnail_src": "https://instagram.fdel3-2.fna.fbcdn.net/v/t51.2885-15/sh0.08/e35/s640x640/90674194_523507438567135_9049331123891284988_n.jpg?_nc_ht=instagram.fdel3-2.fna.fbcdn.net&_nc_cat=107&_nc_ohc=MB1vL-b8YyIAX-v37_I&oh=791c35946a88de002b0264ecacad9298&oe=5EA54F27"
}