{
    "__typename": "GraphImage",
    "comments_disabled": false,
    "dimensions": {
        "height": 855,
        "width": 1080
    },
    "display_url": "https://instagram.fdel3-1.fna.fbcdn.net/v/t51.2885-15/e35/s1080x1080/91134998_211979463200973_8856938320604146598_n.jpg?_nc_ht=instagram.fdel3-1.fna.fbcdn.net&_nc_cat=109&_nc_ohc=InIuCc7EDSYAX8sws9b&oh=76bc0148a21b370351fde9956601c7c0&oe=5EA539A2",
    "edge_liked_by": {
        "count": 12
    },
    "edge_media_to_caption": {
        "edges": [
            {
                "node": {
                    "text": "\ud835\udd6f\ud835\udd94\ud835\udd93'\ud835\udd99 \ud835\udd9c\ud835\udd86\ud835\udd8e\ud835\udd99 \ud835\udd8b\ud835\udd94\ud835\udd97 \ud835\udd8a\ud835\udd9b\ud835\udd8a\ud835\udd97\ud835\udd9e\ud835\udd99\ud835\udd8d\ud835\udd8e\ud835\udd93\ud835\udd8c \ud835\udd99\ud835\udd94 \ud835\udd87\ud835\udd8a \ud835\udd95\ud835\udd8a\ud835\udd97\ud835\udd8b\ud835\udd8a\ud835\udd88\ud835\udd99 \ud835\udd87\ud835\udd8a\ud835\udd8b\ud835\udd94\ud835\udd97\ud835\udd8a \ud835\udd9e\ud835\udd94\ud835\udd9a \ud835\udd89\ud835\udd8a\ud835\udd88\ud835\udd8e\ud835\udd89\ud835\udd8a \ud835\udd99\ud835\udd94 \ud835\udd8a\ud835\udd93\ud835\udd8f\ud835\udd94\ud835\udd9e \ud835\udd9e\ud835\udd94\ud835\udd9a\ud835\udd97 \ud835\udd91\ud835\udd8e\ud835\udd8b\ud835\udd8a.\u2764 \ud835\udd75\ud835\udd94\ud835\udd9e\ud835\udd88\ud835\udd8a \ud835\udd78\ud835\udd8a\ud835\udd9e\ud835\udd8a\ud835\udd97\n.\n.\n.\n.\n@_catch_moment_with_nadinski\n#exploremore #adventure #travergram #mirissa #weligama  #wanderlust #adventureseeker #doyourtravel #travelmore #goexplore #bikini #ocean #worldtravelpics #beach #travel #vacation #awesomeearth #beautifuldestinations #worldplaces #unawatuna \n#bestvacations #bestplacetogo #travelawesome\n#paradise #ekcrew #cabincrewlife #srilankatravel\n@visit_srilanka_\n@thingstodoinsrilanka\n@srilanka.go\n\u2022 \u2022 \u2022 \u2022 \u2022\n#portrait  #adclicks"
                }
            }
        ]
    },
    "edge_media_to_comment": {
        "count": 0
    },
    "id": "2272814412847311855",
    "is_video": false,
    "owner": {
        "id": "307225582"
    },
    "shortcode": "B-KqKqmJuvv",
    "taken_at_timestamp": 1585160613,
    "thumbnail_src": "https://instagram.fdel3-1.fna.fbcdn.net/v/t51.2885-15/sh0.08/e35/c150.0.1140.1140a/s640x640/91134998_211979463200973_8856938320604146598_n.jpg?_nc_ht=instagram.fdel3-1.fna.fbcdn.net&_nc_cat=109&_nc_ohc=InIuCc7EDSYAX8sws9b&oh=c7c81b803f266435c10df83cec5b6d84&oe=5EA4B4C8"
}