{
    "__typename": "GraphImage",
    "comments_disabled": false,
    "dimensions": {
        "height": 1080,
        "width": 1080
    },
    "display_url": "https://instagram.fdel3-2.fna.fbcdn.net/v/t51.2885-15/e35/s1080x1080/85244774_142290470619331_4281278676182704075_n.jpg?_nc_ht=instagram.fdel3-2.fna.fbcdn.net&_nc_cat=107&_nc_ohc=7eKlo__wRtYAX81pWlu&oh=12a60311dc6ff8562b0749b2a516b376&oe=5EA34194",
    "edge_liked_by": {
        "count": 5
    },
    "edge_media_to_caption": {
        "edges": [
            {
                "node": {
                    "text": "#bleibtgesund\ud83c\udf40 \ud83d\ude4f\ud83d\ude4f\ud83d\ude4f\u2600\ufe0f #nature #sky #sun #summer #beach #beautiful #pretty #sunset #sunrise #blue #flowers #night #tree #twilight #clouds #beauty #light #cloudporn #photooftheday #love #green #skylovers #dusk #weather #day #red #mothernature"
                }
            }
        ]
    },
    "edge_media_to_comment": {
        "count": 1
    },
    "id": "2272816245253028459",
    "is_video": false,
    "owner": {
        "id": "4388825869"
    },
    "shortcode": "B-KqlVKCzpr",
    "taken_at_timestamp": 1585160831,
    "thumbnail_src": "https://instagram.fdel3-2.fna.fbcdn.net/v/t51.2885-15/sh0.08/e35/s640x640/85244774_142290470619331_4281278676182704075_n.jpg?_nc_ht=instagram.fdel3-2.fna.fbcdn.net&_nc_cat=107&_nc_ohc=7eKlo__wRtYAX81pWlu&oh=c41c664d29319f5adf5dd9385c4817e1&oe=5EA481A5"
}