{
    "__typename": "GraphImage",
    "comments_disabled": false,
    "dimensions": {
        "height": 1350,
        "width": 1080
    },
    "display_url": "https://instagram.fdel3-1.fna.fbcdn.net/v/t51.2885-15/e35/p1080x1080/90977731_137504234477934_4368653762268556138_n.jpg?_nc_ht=instagram.fdel3-1.fna.fbcdn.net&_nc_cat=106&_nc_ohc=W_0D_fJP2n0AX_Km_xm&oh=323507ee58073ca142580c01c8dbf9b7&oe=5EA42578",
    "edge_liked_by": {
        "count": 41
    },
    "edge_media_to_caption": {
        "edges": [
            {
                "node": {
                    "text": "Everyone should believe in something. - I believe I should go to the beach \ud83c\udf1e"
                }
            }
        ]
    },
    "edge_media_to_comment": {
        "count": 1
    },
    "id": "2272812464173657955",
    "is_video": false,
    "owner": {
        "id": "34614813"
    },
    "shortcode": "B-KpuTwJq9j",
    "taken_at_timestamp": 1585160380,
    "thumbnail_src": "https://instagram.fdel3-1.fna.fbcdn.net/v/t51.2885-15/sh0.08/e35/c0.180.1440.1440a/s640x640/90977731_137504234477934_4368653762268556138_n.jpg?_nc_ht=instagram.fdel3-1.fna.fbcdn.net&_nc_cat=106&_nc_ohc=W_0D_fJP2n0AX_Km_xm&oh=9f4ff701399ce132f714e819b9c2ae96&oe=5EA443E5"
}