{
    "__typename": "GraphImage",
    "comments_disabled": false,
    "dimensions": {
        "height": 1306,
        "width": 1080
    },
    "display_url": "https://instagram.fdel3-2.fna.fbcdn.net/v/t51.2885-15/e35/90705191_149354539719103_1126698740639771109_n.jpg?_nc_ht=instagram.fdel3-2.fna.fbcdn.net&_nc_cat=107&_nc_ohc=H6i4I6j8AisAX-CYK6l&oh=124add0692929024fbc9323e3804ba93&oe=5EA4342D",
    "edge_liked_by": {
        "count": 8
    },
    "edge_media_to_caption": {
        "edges": [
            {
                "node": {
                    "text": "Trying to replicate some better days \ud83c\udfdd #QuarantineGotMeLike \nStill think I should have stayed on an island."
                }
            }
        ]
    },
    "edge_media_to_comment": {
        "count": 3
    },
    "id": "2272815535972940776",
    "is_video": false,
    "owner": {
        "id": "409388935"
    },
    "shortcode": "B-KqbAlp_vo",
    "taken_at_timestamp": 1585160747,
    "thumbnail_src": "https://instagram.fdel3-2.fna.fbcdn.net/v/t51.2885-15/sh0.08/e35/c0.113.1080.1080a/s640x640/90705191_149354539719103_1126698740639771109_n.jpg?_nc_ht=instagram.fdel3-2.fna.fbcdn.net&_nc_cat=107&_nc_ohc=H6i4I6j8AisAX-CYK6l&oh=733fa15aa7da733bf19a98c1b8321ba4&oe=5EA5C088"
}