{
    "__typename": "GraphImage",
    "comments_disabled": false,
    "dimensions": {
        "height": 1080,
        "width": 1080
    },
    "display_url": "https://instagram.fdel3-2.fna.fbcdn.net/v/t51.2885-15/e35/90399821_231894734667682_1495751559155329910_n.jpg?_nc_ht=instagram.fdel3-2.fna.fbcdn.net&_nc_cat=110&_nc_ohc=Jz31_wSOOX0AX9PO0fE&oh=c5aa64ac5741b9a202df61c957d8a3db&oe=5EA53E88",
    "edge_liked_by": {
        "count": 27
    },
    "edge_media_to_caption": {
        "edges": [
            {
                "node": {
                    "text": "A portrait is not made in the camera but on either side of it\n\n#tajmahal #macrophotography\n#nature #shotongalaxy #shotforbeebom #teampixel #sunset #incredibleindia #leaves #waterdroplets #agra #7wondersoftheworld #indiaphotography #india #photooftheday #naturelovers #shotfromthegalaxy #shotongalaxy #shotongalaxys9 #shotongalaxys9plus"
                }
            }
        ]
    },
    "edge_media_to_comment": {
        "count": 0
    },
    "id": "2272688385327666091",
    "is_video": false,
    "owner": {
        "id": "12316667042"
    },
    "shortcode": "B-KNguUnJOr",
    "taken_at_timestamp": 1585145589,
    "thumbnail_src": "https://instagram.fdel3-2.fna.fbcdn.net/v/t51.2885-15/sh0.08/e35/s640x640/90399821_231894734667682_1495751559155329910_n.jpg?_nc_ht=instagram.fdel3-2.fna.fbcdn.net&_nc_cat=110&_nc_ohc=Jz31_wSOOX0AX9PO0fE&oh=4b1e1b5f2372faa286ce4bd0e3e0ca53&oe=5EA6D363"
}