{
    "__typename": "GraphImage",
    "comments_disabled": false,
    "dimensions": {
        "height": 640,
        "width": 640
    },
    "display_url": "https://instagram.fdel3-2.fna.fbcdn.net/v/t51.2885-15/e35/91031609_675618989862745_3672967832843151914_n.jpg?_nc_ht=instagram.fdel3-2.fna.fbcdn.net&_nc_cat=101&_nc_ohc=7VKhP6MIc0wAX8WilrB&oh=f7400547eb69f7c772bd341b2bdbedd6&oe=5E7E11BC",
    "edge_liked_by": {
        "count": 2
    },
    "edge_media_to_caption": {
        "edges": [
            {
                "node": {
                    "text": "@prilaga #naturezadivina #naturezamaravilhosa #fotonatura #nature #fotonatural #sunset #naturezabela #apreciadores_natureza #naturezaviva #fotografia #naturezalinda #instanature #amoanatureza #natureza #flowers #pretty #fotonatureza #fotografianatural #fotosdanatureza #instanatureza #beach #lovenature #retratosdanatureza #prilaga #brasilnature #beautiful #euamoanatureza #naturezaurbana #sunrise #naturezaperfeita"
                }
            }
        ]
    },
    "edge_media_to_comment": {
        "count": 0
    },
    "id": "2272814095807237778",
    "is_video": false,
    "owner": {
        "id": "10022944784"
    },
    "shortcode": "B-KqGDVF06S",
    "taken_at_timestamp": 1585160575,
    "thumbnail_src": "https://instagram.fdel3-2.fna.fbcdn.net/v/t51.2885-15/e35/91031609_675618989862745_3672967832843151914_n.jpg?_nc_ht=instagram.fdel3-2.fna.fbcdn.net&_nc_cat=101&_nc_ohc=7VKhP6MIc0wAX8WilrB&oh=f7400547eb69f7c772bd341b2bdbedd6&oe=5E7E11BC"
}