{
    "__typename": "GraphImage",
    "comments_disabled": false,
    "dimensions": {
        "height": 1080,
        "width": 1080
    },
    "display_url": "https://instagram.fdel3-1.fna.fbcdn.net/v/t51.2885-15/e35/23498981_1236984983111918_7154944430238072832_n.jpg?_nc_ht=instagram.fdel3-1.fna.fbcdn.net&_nc_cat=102&_nc_ohc=Ksxs2sjBQNAAX8W9Cq8&oh=b2501269a63ee65f90e18972ca613820&oe=5EA5B7BC",
    "edge_liked_by": {
        "count": 12
    },
    "edge_media_to_caption": {
        "edges": [
            {
                "node": {
                    "text": "@giveaway_iphoneoriginal\nG = Gabung Giveawaynya yuuk\nI = Ikutin rules yg sangat mudah\nV = Vastikan rulesnya dgn benar yaa\nE = Emang kalo rezeki enggak kemana\nA = Aku aja ikutan dan penuh harap\nW = Waah nyesel kalo kamu ngak ikutan\nA = Abis hadiahnya menggiurkan\nY = Yeeey tunggu apalagi\n_\nI = Iphone original loh hadiahnya\nP = Pasti semua pd berharap\nH = Hanya untuk 100 follower pertama yaa\nO = Oh iyaa\nN = No Baper yaa\nE = Extra sabaar yg belum rezeki\nO = Oma opa ibu bapak adik kakak\nR = Relain yg menang hadiah ini\nI = Ikhlasnya jgn lupa yaa\nG = Gimapun caranya hihihi\nI = InshaAllah Rezeki sayaa dah\nN = Niat udah rules udah doanya ngak ketinggalan\nA = Apapun keputusan juri tidak bisa diganggu gugat\nL = Lari pagi kekota kendal, semoga dapet iphone original.. #giveaway\u00a0#giveawayiphone\u00a0#giveawayiphone6#iphone6gratis\u00a0#iphone6s\u00a0#hadiahiphone#giveawayiphone7#giveawayiphone5s#giveawayiphone7plus#giveawayiwatch#followmy#l#lfl#murah#gratisiphone#freeiphone#gratisongkir #gratisongkirtokopedia #gratis#freeiwatch#murahbanget"
                }
            }
        ]
    },
    "edge_media_to_comment": {
        "count": 1
    },
    "id": "1620415969946351943",
    "is_video": false,
    "owner": {
        "id": "2172790052"
    },
    "shortcode": "BZ8371FBblH",
    "taken_at_timestamp": 1507388658,
    "thumbnail_src": "https://instagram.fdel3-1.fna.fbcdn.net/v/t51.2885-15/sh0.08/e35/s640x640/23498981_1236984983111918_7154944430238072832_n.jpg?_nc_ht=instagram.fdel3-1.fna.fbcdn.net&_nc_cat=102&_nc_ohc=Ksxs2sjBQNAAX8W9Cq8&oh=75e916bf124871b5cda82dd5fd21ee1b&oe=5EA39E02"
}