{
    "__typename": "GraphImage",
    "comments_disabled": false,
    "dimensions": {
        "height": 1350,
        "width": 1080
    },
    "display_url": "https://instagram.fdel3-2.fna.fbcdn.net/v/t51.2885-15/e35/46058136_214111446152257_1097393865571663968_n.jpg?_nc_ht=instagram.fdel3-2.fna.fbcdn.net&_nc_cat=101&_nc_ohc=uWqWd7TGFtMAX-HwOJV&oh=76a0a6a51d03fe48be8200347a716766&oe=5EA3FEFF",
    "edge_liked_by": {
        "count": 110
    },
    "edge_media_to_caption": {
        "edges": [
            {
                "node": {
                    "text": "P S A mindless scroller- I need YOUR help! I feel a little weird posting this but then I thought \u201cwhat the heck\u201d, so many of you have been following my journey & contributing to this milestone.. I need to be sharing this with everyone! \ud83c\udf1f .\nit may be 50 degrees in Tampa but all I\u2019m dreaming about is being on an all-expense paid vacation courtesy of @rodanfields to Los Cabo\u2019s, Mexico w/ my husband \ud83d\udc59\n.\nwell, I\u2019m so close to earning it & guess what that means? that YOU who has been waiting for the perfect moment to try the #1 premium skincare brand is about to get a really sweet deal! I help you fall in love w/ your skin + lashes at a major discount & you help me earn this trip\ud83d\udc4f\ud83c\udffb team work makes the dream work!\n.\nI have 33 days to help -f o r t y- of you so I have limited discounts up for grabs! Hit up my DM\u2019s if you want that to be you \ud83d\udd7a\ud83c\udffcI can\u2019t even believe this is about to be a reality, all I can say is THANK YOU for letting me be your skincare girl! You are the reason this will happen \ud83d\ude07 #lifechangingskincare"
                }
            }
        ]
    },
    "edge_media_to_comment": {
        "count": 10
    },
    "id": "1922870288606025485",
    "is_video": false,
    "owner": {
        "id": "2344779007"
    },
    "shortcode": "BqvaFb1g9cN",
    "taken_at_timestamp": 1543444022,
    "thumbnail_src": "https://instagram.fdel3-2.fna.fbcdn.net/v/t51.2885-15/sh0.08/e35/c0.135.1080.1080a/s640x640/46058136_214111446152257_1097393865571663968_n.jpg?_nc_ht=instagram.fdel3-2.fna.fbcdn.net&_nc_cat=101&_nc_ohc=uWqWd7TGFtMAX-HwOJV&oh=cc8f074b39c8585cc1f29743e44ed2a1&oe=5EA572F3"
}