{
    "__typename": "GraphImage",
    "comments_disabled": false,
    "dimensions": {
        "height": 607,
        "width": 1080
    },
    "display_url": "https://instagram.fdel3-2.fna.fbcdn.net/v/t51.2885-15/e35/47690999_1969908846441335_5910182988566027108_n.jpg?_nc_ht=instagram.fdel3-2.fna.fbcdn.net&_nc_cat=111&_nc_ohc=PBCvBxN7L7MAX9eq3UJ&oh=81c09299d0477a5247bfce50ca716f0a&oe=5EA4FCC4",
    "edge_liked_by": {
        "count": 26
    },
    "edge_media_to_caption": {
        "edges": [
            {
                "node": {
                    "text": "Congrats to the 8 people that won the iphone x, if you didn\u2019t win, then here is your chance to enter the Macbook giveaway....Dm me to get yours delivered to you....... Macbook pro 2017......... #Macbook #Mackbookpro #Apple #applewatch #freemac #Freeapple #Freemacbook #applelaptop #technology #giveaway  #giveawaycontest #Freegiveaway #Iphonex #iphonexsmax #iphonexr #iphone #iphone8plus #freeiphone #iphonegiveaway"
                }
            }
        ]
    },
    "edge_media_to_comment": {
        "count": 0
    },
    "id": "1949379606328749680",
    "is_video": false,
    "owner": {
        "id": "8498110782"
    },
    "shortcode": "BsNlmx3na5w",
    "taken_at_timestamp": 1546604179,
    "thumbnail_src": "https://instagram.fdel3-2.fna.fbcdn.net/v/t51.2885-15/e35/c224.0.576.576a/47690999_1969908846441335_5910182988566027108_n.jpg?_nc_ht=instagram.fdel3-2.fna.fbcdn.net&_nc_cat=111&_nc_ohc=PBCvBxN7L7MAX9eq3UJ&oh=2d08e740a4e78077b328540ace333cd7&oe=5EA527C7"
}