{
    "__typename": "GraphImage",
    "comments_disabled": false,
    "dimensions": {
        "height": 1080,
        "width": 1080
    },
    "display_url": "https://instagram.fdel3-2.fna.fbcdn.net/v/t51.2885-15/e35/s1080x1080/71595121_549638052248237_4562728428257595282_n.jpg?_nc_ht=instagram.fdel3-2.fna.fbcdn.net&_nc_cat=105&_nc_ohc=jYF-ndWiOUsAX812Gez&oh=c37ecee9c13dd491a739d88a758e211e&oe=5EA5F267",
    "edge_liked_by": {
        "count": 4
    },
    "edge_media_to_caption": {
        "edges": [
            {
                "node": {
                    "text": "HAPPY TACO TUESDAY H-TOWN!! SCHEDULES ARE FILLING FAST!! BEAT THE HOLIDAY RUSH AND CALL US TODAY!!!! Be sure to take advantage of your insurance benefits before the end of year, USE THEM\ud83d\ude4c\ud83c\udffdOR LOSE THEM\ud83d\ude14CALL US TODAY!! (291)813-5780\n#klein #springTx #willowbrook #houISD #aldine #stateHwy249 #frenos #smile #ortho #freeAirPods #sonrisa #watchEmGrow #SSHOUTX #SSFam #cantStopWontStop #babyTeethMatter #weWontBeBeat #drSonny #drKim #teVeoPronto #llamenosHoy #callUsToday #whyWait #seeYouSoon"
                }
            }
        ]
    },
    "edge_media_to_comment": {
        "count": 0
    },
    "id": "2180844744614522744",
    "is_video": false,
    "owner": {
        "id": "15769988268"
    },
    "shortcode": "B5D6r2ZBq94",
    "taken_at_timestamp": 1574196974,
    "thumbnail_src": "https://instagram.fdel3-2.fna.fbcdn.net/v/t51.2885-15/sh0.08/e35/s640x640/71595121_549638052248237_4562728428257595282_n.jpg?_nc_ht=instagram.fdel3-2.fna.fbcdn.net&_nc_cat=105&_nc_ohc=jYF-ndWiOUsAX812Gez&oh=ca2a7a8df077776cb3533d0fcd74c52a&oe=5EA3CA52"
}