{
    "__typename": "GraphImage",
    "comments_disabled": false,
    "dimensions": {
        "height": 810,
        "width": 1080
    },
    "display_url": "https://instagram.fdel3-1.fna.fbcdn.net/v/t51.2885-15/e35/69761759_147433166563659_6784645206260164094_n.jpg?_nc_ht=instagram.fdel3-1.fna.fbcdn.net&_nc_cat=103&_nc_ohc=Bgt79-zhvqEAX_AVUCq&oh=97024c23517ee4b477d0341d3c6809e0&oe=5EA4055A",
    "edge_liked_by": {
        "count": 22
    },
    "edge_media_to_caption": {
        "edges": [
            {
                "node": {
                    "text": "All type of phone available. DM us for more details. Christmas sales started. Price list here.\nLTS MOBILE & ACCESSORIES ENTERPRISE \nApple Airpods 2 New\nRM 620.00\nOne year Apple Warranty *Apple iPad* Used\nMini 16GB Wifi : *RM 335*\nMini 3 16GB Wifi+Cellular : *RM 680*\n5th Gen 2017 32GB Wifi+Cellular : *RM 930*\nAir 2nd Gen 16GB Wifi+Cellular : *RM 870* *Sony Au : Global Firmware* Used\nZ3 (3/32) : *RM 225* Fullset\nZ4 (3/32) : *RM 235* Fullset\nXZ (3/32) : *RM 295* Fullset\nXZs (4/32) : *RM 325* Fullset\nXZ1 (4/64) : *RM 560* Fullset *Oppo* Used\nA37 (2/16) : *RM 295* Fullset *Google Phone* Used\nPixel (4/32) : *RM 385* Fullset\nPixel (4/128) : *RM 465* Fullset\nPixel 2XL (4/64) : *RM 885* Fullset Ori\nPixel 2XL (4/128) : *RM 1025* Fullset Ori *Samsung Dual Sim* Used\nNote 8 64GB : *RM 1205* *Sony Dual Sim* New\nZ3 (3/16) *RM 430* Fullset Ori\n\n#####BIG SALE##### *Apple Import set* Used\n\u2022Like New Condition\n\niPhone 5S Fullset\n\ud83c\udf4e32GB *RM 325*| Grade B\n\ud83c\udf4e64GB *RM 355*| Grade B\n\niPhone 6 Fullset\n\ud83c\udf4e16GB *RM 420*|\n\ud83c\udf4e32GB *RM 460*|\n\ud83c\udf4e64GB *RM 500*|\n\ud83c\udf4e128GB *RM 540*\n\niPhone 6Plus Fullset\n\ud83c\udf4e16GB *RM 530*|\n\ud83c\udf4e64GB *RM 680*|\n\ud83c\udf4e128GB *RM 730*| iPhone 6S Fullset\n\ud83c\udf4e16GB *RM 520*|\n\ud83c\udf4e32GB *RM 570*|\n\ud83c\udf4e64GB *RM 620*|\n\ud83c\udf4e128GB *RM 670*| iPhone 6SP Fullset\n\ud83c\udf4e64GB *RM 880*| iPhone SE Fullset\n\ud83c\udf4e16GB *RM 410*|\n\ud83c\udf4e32GB *RM 480*| iPhone 7 Fullset\n\ud83c\udf4e32GB *RM 790*|\n\ud83c\udf4e128GB *RM 910*| iPhone 7Plus Fullset\n\ud83c\udf4e32GB *RM 1270*|\n\ud83c\udf4e128GB *RM 1400*|\n\ud83c\udf4e256GB *RM 1470*| iPhone 8 Fullset\n\ud83c\udf4e64GB *RM 1289*| iPhone 8Plus Fullset\n\ud83c\udf4e64GB *RM 1700*| iPhone X Fullset\n\ud83c\udf4e64GB *RM 2140*|\n\ud83c\udf4e256GB *RM 2340*| iPhone XR\u00a0 Fullset\n\ud83c\udf4e64GB *RM 2200*| iPhone XS Max Fullset\n\ud83c\udf4e256GB *RM 3200* My-set\n\ud83c\udf4e256GB *RM 3100* LL-set \nPostage Fee : RM 15\n\ud83d\udc4d\ud83c\udffbFree Insurance Covered !\n\ud83d\udc4d\ud83c\udffbParcel Lost Full Refund ! \ud83d\udc4d\ud83c\udffbOne Month Warranty\n\u2022Hardware/Software/Motherboad\n\nWarranty Not Cover on\n1.Battery Fast Drain Issues\n2.Water Damage\n3.Dropped set Lcd Cracked\n4.Sticker Warranty Damaged/Removed\n#Ltsmobile\n#christmassales\n#giveawayiphone\n#salesiphone\n#airpod\n#freeairpods\nWhatsapp : 0192176903 - Tavin"
                }
            }
        ]
    },
    "edge_media_to_comment": {
        "count": 0
    },
    "id": "2190468851079562998",
    "is_video": false,
    "owner": {
        "id": "18971050645"
    },
    "shortcode": "B5mG9CAJ8b2",
    "taken_at_timestamp": 1575344257,
    "thumbnail_src": "https://instagram.fdel3-1.fna.fbcdn.net/v/t51.2885-15/sh0.08/e35/c135.0.810.810a/s640x640/69761759_147433166563659_6784645206260164094_n.jpg?_nc_ht=instagram.fdel3-1.fna.fbcdn.net&_nc_cat=103&_nc_ohc=Bgt79-zhvqEAX_AVUCq&oh=fc7a2c3754a803d166efd7bcd52fbf8e&oe=5EA560FB"
}