{
    "__typename": "GraphImage",
    "comments_disabled": false,
    "dimensions": {
        "height": 1080,
        "width": 1080
    },
    "display_url": "https://instagram.fdel3-2.fna.fbcdn.net/v/t51.2885-15/e35/79272968_162733598273257_4989595371576810754_n.jpg?_nc_ht=instagram.fdel3-2.fna.fbcdn.net&_nc_cat=101&_nc_ohc=japfjktM0qoAX8G0-29&oh=78ed9443dc6c430feb9d3006a15f292d&oe=5EA43728",
    "edge_liked_by": {
        "count": 300
    },
    "edge_media_to_caption": {
        "edges": [
            {
                "node": {
                    "text": "Funda de baymax para airpods \u2728\n\u2022$300\n.\n.\n~ env\u00edos a todo M\u00e9xico \ud83c\uddf2\ud83c\uddfd #cdmx #tienda #fudas #funda #fundasairpods #fundaairpods #airpods #airpodsfunda #airpodsfundas #fundasairpodscdmx #ciudaddemexico #airpodscase #airpods\ud83c\udfa7 #airpodscases #airpodscases #airpodscdmx #airpodsapple #airpodsstyle #airpodscover #airpodsaccessories #freeairpods #airpodsgiveaway #disney #followforfollowback #follow\uff4de #followbackinstantly #follower #likeforlikes #like4likes"
                }
            }
        ]
    },
    "edge_media_to_comment": {
        "count": 6
    },
    "id": "2191831206190224936",
    "is_video": false,
    "owner": {
        "id": "6655803003"
    },
    "shortcode": "B5q8t6ElZYo",
    "taken_at_timestamp": 1575506662,
    "thumbnail_src": "https://instagram.fdel3-2.fna.fbcdn.net/v/t51.2885-15/sh0.08/e35/s640x640/79272968_162733598273257_4989595371576810754_n.jpg?_nc_ht=instagram.fdel3-2.fna.fbcdn.net&_nc_cat=101&_nc_ohc=japfjktM0qoAX8G0-29&oh=9834d1bac63eb0e0380459d103471c08&oe=5EA58AC3"
}