{
    "__typename": "GraphImage",
    "comments_disabled": false,
    "dimensions": {
        "height": 810,
        "width": 1080
    },
    "display_url": "https://instagram.fdel3-2.fna.fbcdn.net/v/t51.2885-15/e35/s1080x1080/78709967_165572551475129_5371636467623946585_n.jpg?_nc_ht=instagram.fdel3-2.fna.fbcdn.net&_nc_cat=105&_nc_ohc=te6zSlFZkMIAX_YVVuX&oh=0900af2edb9516f7ae11a26500b78524&oe=5EA50DE6",
    "edge_liked_by": {
        "count": 24
    },
    "edge_media_to_caption": {
        "edges": [
            {
                "node": {
                    "text": "The deadline is today! Renew your lease today and be entered to win one of these awesome prizes as part of our Renewal Giveaway! \ud83c\udf84\ud83d\udcf1\ud83c\udfa7\ud83c\udf81\ud83d\udeb2 #renewalgiveaway #freeipad #freebike #freeairpods #liveatcoastalclub"
                }
            }
        ]
    },
    "edge_media_to_comment": {
        "count": 0
    },
    "id": "2198155496668836079",
    "is_video": false,
    "owner": {
        "id": "560217091"
    },
    "shortcode": "B6BasckBLDv",
    "taken_at_timestamp": 1576260576,
    "thumbnail_src": "https://instagram.fdel3-2.fna.fbcdn.net/v/t51.2885-15/sh0.08/e35/c180.0.1080.1080a/s640x640/78709967_165572551475129_5371636467623946585_n.jpg?_nc_ht=instagram.fdel3-2.fna.fbcdn.net&_nc_cat=105&_nc_ohc=te6zSlFZkMIAX_YVVuX&oh=2cd03fe3459eeade6ecf6ee4668cc025&oe=5EA71CA5"
}