{
    "__typename": "GraphImage",
    "comments_disabled": false,
    "dimensions": {
        "height": 750,
        "width": 750
    },
    "display_url": "https://instagram.fdel3-1.fna.fbcdn.net/v/t51.2885-15/e35/79145332_1032521993781513_1076665330258455158_n.jpg?_nc_ht=instagram.fdel3-1.fna.fbcdn.net&_nc_cat=109&_nc_ohc=Iygna8Ym37YAX8vvM2n&oh=254b099835f92ecf4d9757ff68e0b4bf&oe=5EA38B30",
    "edge_liked_by": {
        "count": 9
    },
    "edge_media_to_caption": {
        "edges": [
            {
                "node": {
                    "text": "\ud83d\ude0d@free.airpods4u is giving away *FREE* AirPods!! All you have to do is be following him!!! \ud83d\udc40WE ARE CHECKING!!!\ud83d\udd25\ud83d\ude02#airpods#giveaway#freeairpods#freegiveaway#mebeast#fortnite#freeiphone\n#####meem#meme#memes#dankmemes#fortnite#fortnitememes#lol#lmao#lmfao#jokes#followforfollow#pride#gaypride#nigga#christmas#faze#fazetfup#fortnitecontent"
                }
            }
        ]
    },
    "edge_media_to_comment": {
        "count": 0
    },
    "id": "2203342880986546461",
    "is_video": false,
    "owner": {
        "id": "4990611071"
    },
    "shortcode": "B6T2K0rlsEd",
    "taken_at_timestamp": 1576878961,
    "thumbnail_src": "https://instagram.fdel3-1.fna.fbcdn.net/v/t51.2885-15/sh0.08/e35/s640x640/79145332_1032521993781513_1076665330258455158_n.jpg?_nc_ht=instagram.fdel3-1.fna.fbcdn.net&_nc_cat=109&_nc_ohc=Iygna8Ym37YAX8vvM2n&oh=768b39e8c679afe23eacd88bbaba09f7&oe=5EA50696"
}