{
    "__typename": "GraphImage",
    "comments_disabled": false,
    "dimensions": {
        "height": 1070,
        "width": 1080
    },
    "display_url": "https://instagram.fdel3-1.fna.fbcdn.net/v/t51.2885-15/fr/e15/s1080x1080/82044415_607801953363867_7465661207839251241_n.jpg?_nc_ht=instagram.fdel3-1.fna.fbcdn.net&_nc_cat=103&_nc_ohc=BpXybxMlaRgAX9XUIpw&oh=149e13b2e9c351a875c518ac88ad165a&oe=5EA4199E",
    "edge_liked_by": {
        "count": 11
    },
    "edge_media_to_caption": {
        "edges": [
            {
                "node": {
                    "text": "\ud83d\udc49\ud83d\udc49 Win an #iphone11 or #iphone11pro giveaway \ud83d\udc49\ud83d\udc49 Link in bio @freeiphonewin247\nTo win this contest You need to\n\u27a1 Like & Share this contest\n\u27a1 Follow this account\n\u27a1Complete your entry\n\n#winiphone #winiphone11pro #winiphone11 #freeiphone #freeiphones #freeiphone11pro #freeiphone11 #freeiphonegiveaway #getfreeiphone #getfreeiphone11pro #getfreeiphone11 #getfreeairpods #freeairpods"
                }
            }
        ]
    },
    "edge_media_to_comment": {
        "count": 0
    },
    "id": "2213380202535826023",
    "is_video": false,
    "owner": {
        "id": "7103339139"
    },
    "shortcode": "B63gZE1B7Jn",
    "taken_at_timestamp": 1578075503,
    "thumbnail_src": "https://instagram.fdel3-1.fna.fbcdn.net/v/t51.2885-15/e15/c5.0.1070.1070a/s640x640/82044415_607801953363867_7465661207839251241_n.jpg?_nc_ht=instagram.fdel3-1.fna.fbcdn.net&_nc_cat=103&_nc_ohc=BpXybxMlaRgAX9XUIpw&oh=5cdc31561571c666a7061884966aab56&oe=5EA352F6"
}