{
    "__typename": "GraphImage",
    "comments_disabled": false,
    "dimensions": {
        "height": 1080,
        "width": 1080
    },
    "display_url": "https://instagram.fdel3-1.fna.fbcdn.net/v/t51.2885-15/e35/82448663_909368189478930_4379142547649531427_n.jpg?_nc_ht=instagram.fdel3-1.fna.fbcdn.net&_nc_cat=106&_nc_ohc=mIUpXCQU_bcAX_-kcRz&oh=cf224daa46a5d9d64cb6c4ec55df685c&oe=5EA3DC4D",
    "edge_liked_by": {
        "count": 165
    },
    "edge_media_to_caption": {
        "edges": [
            {
                "node": {
                    "text": "Funda Airpods Bimo \u2728\n\u2022$250\n.\n.\n~ env\u00edos a todo M\u00e9Xico \ud83c\uddf2\ud83c\uddfd #cdmx #tienda #fudas #funda #fundasairpods #fundaairpods #airpods #airpodsfunda #airpodsfundas #fundasairpodscdmx #ciudaddemexico #airpodscase #airpods\ud83c\udfa7 #airpodscases #airpodscases #airpodscdmx #airpodsapple #airpodsstyle #airpodscover #airpodsaccessories #freeairpods #airpodsgiveaway #disney #followforfollowback #follow\uff4de #followbackinstantly #follower #likeforlikes #like4likes"
                }
            }
        ]
    },
    "edge_media_to_comment": {
        "count": 0
    },
    "id": "2234378381390291039",
    "is_video": false,
    "owner": {
        "id": "6655803003"
    },
    "shortcode": "B8CG0y0lKBf",
    "taken_at_timestamp": 1580578681,
    "thumbnail_src": "https://instagram.fdel3-1.fna.fbcdn.net/v/t51.2885-15/sh0.08/e35/s640x640/82448663_909368189478930_4379142547649531427_n.jpg?_nc_ht=instagram.fdel3-1.fna.fbcdn.net&_nc_cat=106&_nc_ohc=mIUpXCQU_bcAX_-kcRz&oh=193b00fceb9164a9b5a4c062baf0b497&oe=5EA68D2A"
}