{
    "__typename": "GraphImage",
    "comments_disabled": false,
    "dimensions": {
        "height": 342,
        "width": 320
    },
    "display_url": "https://instagram.fdel3-1.fna.fbcdn.net/v/t51.2885-15/e35/89914185_2614885075423236_2010811446010875193_n.jpg?_nc_ht=instagram.fdel3-1.fna.fbcdn.net&_nc_cat=100&_nc_ohc=iBAt4s5fKzQAX8nAKMC&oh=ecbd4dd76b5381846db18caad852c281&oe=5EA5AA98",
    "edge_liked_by": {
        "count": 52
    },
    "edge_media_to_caption": {
        "edges": [
            {
                "node": {
                    "text": "#McDonaldsMemes#Meme# #Memes #mcmeme#McDonaldsmeme#mcdonalds#dankmemes#funnymemes#memesdaily#mcdonaldscanada#bigmac#hamburger#burger#employee#customerserviceproblems#aripods#freeairpods#giveaway#hashbrowns#hashbrown#wegotfoodathome#fastfoodmemes#kitchen#kitchenmemes"
                }
            }
        ]
    },
    "edge_media_to_comment": {
        "count": 2
    },
    "id": "2263359229838298825",
    "is_video": false,
    "owner": {
        "id": "3256245329"
    },
    "shortcode": "B9pETpNnQ7J",
    "taken_at_timestamp": 1584033467,
    "thumbnail_src": "https://instagram.fdel3-1.fna.fbcdn.net/v/t51.2885-15/e35/c0.11.320.320a/89914185_2614885075423236_2010811446010875193_n.jpg?_nc_ht=instagram.fdel3-1.fna.fbcdn.net&_nc_cat=100&_nc_ohc=iBAt4s5fKzQAX8nAKMC&oh=a774fe113d97a6ae07f9ff2b9079e696&oe=5EA6FFDF"
}