{
    "__typename": "GraphImage",
    "comments_disabled": false,
    "dimensions": {
        "height": 750,
        "width": 750
    },
    "display_url": "https://instagram.fdel3-2.fna.fbcdn.net/v/t51.2885-15/e35/90356549_2248092938828137_2843350204214220012_n.jpg?_nc_ht=instagram.fdel3-2.fna.fbcdn.net&_nc_cat=101&_nc_ohc=C-UtrgKX0s4AX9i9n_8&oh=084ef9adf23d45ebb0e91c6615cf7975&oe=5EA371B8",
    "edge_liked_by": {
        "count": 4
    },
    "edge_media_to_caption": {
        "edges": [
            {
                "node": {
                    "text": "3 Air Pod Pro Giveaway!!\nEnds in 24HR No Bull Shit Man \u2b07\ufe0f\u2b07\ufe0f\n_________________________\nTo Maybe Win Follow These\nFOLLOW \n@entrepreneur @hoodclips @hoodsite @bighomieblocks \nFollow me, Repost on your story and tag me, like/comment\n\n#giveaway #giveawaycontest #freeairpods #explore #trending #investing #entrepreneur #airpodspro #coronavirus #staysafe #freeshit #instagram #memes #toxicmemes #bored #giveaway #giveawaycontest #freeairpods #explore #trending #investing #entrepreneur #airpodspro #coronavirus #staysafe #freeshit #instagram #memes #toxicmemes #bored"
                }
            }
        ]
    },
    "edge_media_to_comment": {
        "count": 1
    },
    "id": "2271343980744753378",
    "is_video": false,
    "owner": {
        "id": "12581387482"
    },
    "shortcode": "B-Fb1D_A0Di",
    "taken_at_timestamp": 1584985323,
    "thumbnail_src": "https://instagram.fdel3-2.fna.fbcdn.net/v/t51.2885-15/sh0.08/e35/s640x640/90356549_2248092938828137_2843350204214220012_n.jpg?_nc_ht=instagram.fdel3-2.fna.fbcdn.net&_nc_cat=101&_nc_ohc=C-UtrgKX0s4AX9i9n_8&oh=461a9ebae1a0de2a1c321aacdaa533a8&oe=5EA5090E"
}