{
    "__typename": "GraphImage",
    "comments_disabled": false,
    "dimensions": {
        "height": 612,
        "width": 612
    },
    "display_url": "https://instagram.fdel3-1.fna.fbcdn.net/v/t51.2885-15/e15/11202535_906887852711808_1751704933_n.jpg?_nc_ht=instagram.fdel3-1.fna.fbcdn.net&_nc_cat=100&_nc_ohc=jHAAWcW8kXsAX939cj-&oh=6676371eeabe24bcceb741e27656d9c4&oe=5EA40696",
    "edge_liked_by": {
        "count": 26
    },
    "edge_media_to_caption": {
        "edges": [
            {
                "node": {
                    "text": "FOLLOWWWW #ifunny #instagram #yes #followme #awesome#followforfollow #likeforlike #likeforfollow #followforlike #shoutouts #freemacbook #freeiphone  #Hellyeah #instaawesome #onedirection #photography #picoftheday #Comedycentral#JAMARI_SELDERS#getmorefollowers #Free#life #love #laugh #coolpics #beautiful #live #workaholics #truth #Allday"
                }
            }
        ]
    },
    "edge_media_to_comment": {
        "count": 2
    },
    "id": "310790371713472866",
    "is_video": false,
    "owner": {
        "id": "242511525"
    },
    "shortcode": "RQJjJJl9li",
    "taken_at_timestamp": 1351269121,
    "thumbnail_src": "https://instagram.fdel3-1.fna.fbcdn.net/v/t51.2885-15/e15/11202535_906887852711808_1751704933_n.jpg?_nc_ht=instagram.fdel3-1.fna.fbcdn.net&_nc_cat=100&_nc_ohc=jHAAWcW8kXsAX939cj-&oh=6676371eeabe24bcceb741e27656d9c4&oe=5EA40696"
}