{
    "__typename": "GraphImage",
    "comments_disabled": false,
    "dimensions": {
        "height": 640,
        "width": 640
    },
    "display_url": "https://instagram.fdel3-1.fna.fbcdn.net/v/t51.2885-15/e15/10724623_758501324223603_435136637_n.jpg?_nc_ht=instagram.fdel3-1.fna.fbcdn.net&_nc_cat=103&_nc_ohc=-gN_ZoOHSL8AX82f1CN&oh=b678294480d0166581ac3af928fbdd79&oe=5EA37CAF",
    "edge_liked_by": {
        "count": 21
    },
    "edge_media_to_caption": {
        "edges": [
            {
                "node": {
                    "text": "Hurry! Get a #free #ipad or #iwatch when you sign up for a 1 yr subscription of #clientell in the next 7 days!! Get a better ROI guarantee for your #advertising spend and some #freebies ! #instadaily #apple #data #socialmedia #dma14 #tech #analytics #freeipad #freeiwatch #growth #marketing #biz #bigdata #picoftheday #instagood"
                }
            }
        ]
    },
    "edge_media_to_comment": {
        "count": 5
    },
    "id": "832033298964987125",
    "is_video": false,
    "owner": {
        "id": "1528456710"
    },
    "shortcode": "uL-eCKGrz1",
    "taken_at_timestamp": 1413406120,
    "thumbnail_src": "https://instagram.fdel3-1.fna.fbcdn.net/v/t51.2885-15/e15/10724623_758501324223603_435136637_n.jpg?_nc_ht=instagram.fdel3-1.fna.fbcdn.net&_nc_cat=103&_nc_ohc=-gN_ZoOHSL8AX82f1CN&oh=b678294480d0166581ac3af928fbdd79&oe=5EA37CAF"
}